vi/__init__.py
vi/consts.py
vi/version.py
vi/api/__init__.py
vi/api/client.py
vi/api/pagination.py
vi/api/responses.py
vi/api/types.py
vi/api/resources/__init__.py
vi/api/resources/consts.py
vi/api/resources/general.py
vi/api/resources/waiter.py
vi/api/resources/datasets/__init__.py
vi/api/resources/datasets/datasets.py
vi/api/resources/datasets/downloader.py
vi/api/resources/datasets/links.py
vi/api/resources/datasets/responses.py
vi/api/resources/datasets/results.py
vi/api/resources/datasets/types.py
vi/api/resources/datasets/annotations/__init__.py
vi/api/resources/datasets/annotations/annotations.py
vi/api/resources/datasets/annotations/consts.py
vi/api/resources/datasets/annotations/downloader.py
vi/api/resources/datasets/annotations/links.py
vi/api/resources/datasets/annotations/responses.py
vi/api/resources/datasets/annotations/results.py
vi/api/resources/datasets/annotations/types.py
vi/api/resources/datasets/annotations/uploader.py
vi/api/resources/datasets/assets/__init__.py
vi/api/resources/datasets/assets/assets.py
vi/api/resources/datasets/assets/consts.py
vi/api/resources/datasets/assets/downloader.py
vi/api/resources/datasets/assets/links.py
vi/api/resources/datasets/assets/responses.py
vi/api/resources/datasets/assets/results.py
vi/api/resources/datasets/assets/types.py
vi/api/resources/datasets/assets/uploader.py
vi/api/resources/datasets/utils/__init__.py
vi/api/resources/datasets/utils/helper.py
vi/api/resources/flows/__init__.py
vi/api/resources/flows/flows.py
vi/api/resources/flows/links.py
vi/api/resources/flows/responses.py
vi/api/resources/flows/types.py
vi/api/resources/managers/__init__.py
vi/api/resources/managers/downloader.py
vi/api/resources/managers/results.py
vi/api/resources/managers/uploader.py
vi/api/resources/managers/utils/__init__.py
vi/api/resources/managers/utils/progress.py
vi/api/resources/models/__init__.py
vi/api/resources/models/downloader.py
vi/api/resources/models/links.py
vi/api/resources/models/models.py
vi_sdk-0.1.0b4.dist-info/METADATA
vi_sdk-0.1.0b4.dist-info/WHEEL
vi_sdk-0.1.0b4.dist-info/licenses/LICENSE
vi_sdk-0.1.0b4.dist-info/RECORD
